<?xml version="1.0" encoding="UTF-8"?>
<mule xmlns="http://www.mulesoft.org/schema/mule/core" xmlns:apikit="http://www.mulesoft.org/schema/mule/mule-apikit" xmlns:doc="http://www.mulesoft.org/schema/mule/documentation" xmlns:ee="http://www.mulesoft.org/schema/mule/ee/core" xmlns:http="http://www.mulesoft.org/schema/mule/http" xmlns:xsi="http://www.w3.org/2001/XMLSchema-instance" xsi:schemaLocation="http://www.mulesoft.org/schema/mule/core http://www.mulesoft.org/schema/mule/core/current/mule.xsd http://www.mulesoft.org/schema/mule/http http://www.mulesoft.org/schema/mule/http/current/mule-http.xsd http://www.mulesoft.org/schema/mule/mule-apikit http://www.mulesoft.org/schema/mule/mule-apikit/current/mule-apikit.xsd http://www.mulesoft.org/schema/mule/ee/core http://www.mulesoft.org/schema/mule/ee/core/current/mule-ee.xsd ">
    <http:listener-config name="salesforce-account-httpListenerConfig">
        <http:listener-connection host="0.0.0.0" port="8081" />
    </http:listener-config>
    <apikit:config name="salesforce-account-config" api="salesforce-account.raml" outboundHeadersMapName="outboundHeaders" httpStatusVarName="httpStatus" />
    <flow name="salesforce-account-main">
        <http:listener config-ref="salesforce-account-httpListenerConfig" path="/api/*">
            <http:response statusCode="#[vars.httpStatus default 200]">
                <http:headers>#[vars.outboundHeaders default {}]</http:headers>
            </http:response>
            <http:error-response statusCode="#[vars.httpStatus default 500]">
                <http:body>#[payload]</http:body>
                <http:headers>#[vars.outboundHeaders default {}]</http:headers>
            </http:error-response>
        </http:listener>
        <apikit:router config-ref="salesforce-account-config" />
        <error-handler ref="allErrorHandler" />
    </flow>
    <flow name="salesforce-account-console">
        <http:listener config-ref="salesforce-account-httpListenerConfig" path="/console/*">
            <http:response statusCode="#[vars.httpStatus default 200]">
                <http:headers>#[vars.outboundHeaders default {}]</http:headers>
            </http:response>
            <http:error-response statusCode="#[vars.httpStatus default 500]">
                <http:body>#[payload]</http:body>
                <http:headers>#[vars.outboundHeaders default {}]</http:headers>
            </http:error-response>
        </http:listener>
        <apikit:console config-ref="salesforce-account-config" />
        <error-handler ref="allErrorHandler" />
    </flow>
    <!-- [STUDIO:"get:\batch:salesforce-account-config"]<flow name="get:\batch:salesforce-account-config">
        <ee:transform doc:name="Transform Message">
            <ee:message>
                <ee:set-payload><![CDATA[%dw 2.0
output application/json
&#45;&#45;-
{
  getExample: {
    message: "success"
  }
} as Object {encoding: "UTF-8", mediaType: "application/json"}&#93;&#93;></ee:set-payload>
            </ee:message>
        </ee:transform>
    </flow> [STUDIO] -->
    <flow name="post:\batch:salesforce-account-config">
        <flow-ref doc:name="getFileFromSFTP-reference" doc:id="2c733392-2351-4487-a4db-ad1b7f85ca1b" name="process_getFileFromSFTP" />
        <error-handler ref="allErrorHandler" />
    </flow>
    <flow name="get:\batch:salesforce-account-config">
        <logger level="INFO" message="get:\batch:salesforce-account-config" />
    </flow>
</mule>
